conversations_about_important_api/__init__.py
conversations_about_important_api/pars.py
conversations_about_important_api-0.1.0.dist-info/METADATA
conversations_about_important_api-0.1.0.dist-info/WHEEL
conversations_about_important_api-0.1.0.dist-info/licenses/LICENSE
conversations_about_important_api-0.1.0.dist-info/RECORD
