Metadata-Version: 2.4
Name: conversations_about_important_api
Version: 0.1.0
Summary: Неофициальное API «разговоров о важном».
Project-URL: Homepage, https://github.com/iamlostshe/conversations-about-important-api
Project-URL: Issues, https://github.com/iamlostshe/conversations-about-important-api/issues
Author-email: iamlostshe <vanamelcikov7275@gmail.com>
Maintainer-email: iamlostshe <vanamelcikov7275@gmail.com>
License-Expression: MIT
License-File: LICENSE
Keywords: api,asyncio,framework,pars,parsing,wrapper
Classifier: Development Status :: 5 - Production/Stable
Classifier: Environment :: Console
Classifier: Intended Audience :: Developers
Classifier: Intended Audience :: System Administrators
Classifier: License :: OSI Approved :: MIT License
Classifier: Programming Language :: Python :: 3.9
Classifier: Programming Language :: Python :: 3.10
Classifier: Programming Language :: Python :: 3.11
Classifier: Programming Language :: Python :: 3.12
Classifier: Programming Language :: Python :: 3.13
Classifier: Programming Language :: Python :: Implementation :: PyPy
Classifier: Topic :: Software Development :: Libraries :: Python Modules
Classifier: Typing :: Typed
Requires-Dist: curl-cffi
Requires-Dist: lxml
